{"onairs": [
  {
    "channelCode": "31",
    "startDate": "2014-01-19T14:26:29.350Z",
    "endDate": "2014-01-19T14:31:08.350Z",
    "type": "SONG",
    "onairType": "PREVIOUS",
    "properties" : [
		{
    		"key" : "ARTISTNAME",
    		"value"  : "Steven Kolacny  piano  "
},		{
    		"key" : "TITLE",
    		"value"  : "5 pianostukken: 2.Menuet - 4.Wals"
},		{
    		"key" : "COMPOSER",
    		"value"  : "Herman Meulemans"
}    ]
},  {
    "channelCode": "31",
    "startDate": "2014-01-21T23:24:29.350Z",
    "endDate": "2014-01-21T23:28:28.350Z",
    "type": "SONG",
    "onairType": "NEXT",
    "properties" : [
		{
    		"key" : "ARTISTNAME",
    		"value"  : "Michael Jackson"
},		{
    		"key" : "TITLE",
    		"value"  : "Tous 3les autres"
},		{
    		"key" : "COMPOSER",
    		"value"  : "Richard Wagner"
}    ]
}, {
    "channelCode": "31",
    "startDate": "2014-01-21T23:24:29.350Z",
    "endDate": "2014-01-21T23:28:28.350Z",
    "type": "SONG",
    "onairType": "NOW",
    "properties" : [
        {
            "key" : "ARTISTNAME",
            "value"  : "Stromae"
},      {
            "key" : "TITLE",
            "value"  : "10 pianostukken: 2.Menuet - 4.Wals"
},      {
            "key" : "COMPOSER",
            "value"  : "Herman Meulemans"
}    ]
}
]}
